{
	"parent_age" : "0",

	"global_msg_age" : "0",
	"global_msg" : "Hello World",

	"win_msg_age" : "0",
	"win_msg" : [
		{
			"about_msg" : "New Wallpaper, bro!"
		}
	],

	"data" : [
		{
			"age" : "0",
			"category" : "new_wall",
			"path" : ""
		},
		{
			"age" : "0",
			"category" : "old_wall",
			"path" : ""
		},
		{
			"age" : "0",
			"category" : "default_wall",
			"path" : "https://raw.githubusercontent.com/averdsoft/ewc/master/root/files/default/default.json"
		},
		{
			"age" : "0",
			"category" : "black_wall",
			"path" : ""
		}
	]
}